{
    "name": "Arena 11: Walls 3",
    "mode": "arena",
    "terrain": [[0, 0, 0, 0, 0, 0],
                [0, 0, 0, 0, 0, 0],
                [0, 0, 0, 0, 0, 0],
                [0, 0, 0, 0, 0, 0],
                [0, 0, 0, 0, 0, 0],
                [0, 0, 0, 0, 0, 0],
                [0, 0, 0, 0, 0, 0],
                [0, 0, 0, 0, 0, 0]],
    "defensiveTiles": [12, 15, 20, 23, 24, 27, 32, 35],
    "struct_walls": {
      "static": [],
      "twoBreak": [],
      "oneBreak": [13, 16, 19, 22, 25, 28, 31, 34]
    },
    "playerStart": [1, 2, 3, 4],
    "enemyStart": [43, 44, 45, 46],
    "enemyData":
    [  {"name": "Chrom",
       "level": 40,
       "rarity": 5,
       "weapon": "Armorslayer+",
       "special": "Bonfire",
       "cskill": "Hone Atk 2",
       "startMove": 1,
       "wallBreak": false
       },
        {"name": "Myrrh",
       "level": 40,
       "rarity": 5,
        "assist": "Reposition",
       "startMove": 1,
       "wallBreak": false
      },
       {"name": "SF!Xander",
       "level": 40,
       "rarity": 5,
       "weapon": "Iron Dagger",
       "assist": "Dance",
       "startMove": 1,
       "wallBreak": false
      },
       {"name": "Soren",
       "level": 40,
       "rarity": 5,
       "weapon": "Rexcalibur",
       "startMove": 1,
       "wallBreak": false
      }
    ]
  }
